cfnsane/__init__.py
cfnsane/loader.py
cfnsane/meta.py
cfnsane/resources/__init__.py
cfnsane/resources/bucket.py
cfnsane/yaml.py
cfnsane-0.0.1.dist-info/LICENSE
cfnsane-0.0.1.dist-info/WHEEL
cfnsane-0.0.1.dist-info/METADATA
cfnsane-0.0.1.dist-info/RECORD
