Metadata-Version: 2.1
Name: cfnsane
Version: 0.0.1
Summary: 
Author: Michael Neil
Author-email: mneil@mneilsworld.com
Requires-Python: >=3.8,<4.0
Classifier: Programming Language :: Python :: 3
Classifier: Programming Language :: Python :: 3.8
Classifier: Programming Language :: Python :: 3.9
Requires-Dist: PyYAML (>=5.3.1,<6.0.0)
Requires-Dist: toml (>=0.10.2,<0.11.0)
Requires-Dist: troposphere (>=2.6.3,<3.0.0)
